PERF/__init__.py
PERF/analyse.py
PERF/annotation.py
PERF/core.py
PERF/fastq_utils.py
PERF/rep_utils.py
PERF/twobit_utils.py
PERF/utils.py
PERF/lib/template.html
PERF/lib/template_fasta.html
PERF/lib/template_fastq.html
PERF/lib/src/all.js
PERF/lib/src/anno_charts.js
PERF/lib/src/apexcharts.min.js
PERF/lib/src/barPlot.js
PERF/lib/src/exporting.js
PERF/lib/src/highcharts.js
PERF/lib/src/init.js
PERF/lib/src/jquery-3.5.0.min.js
PERF/lib/src/jquery.multi-select.min.js
PERF/lib/src/linePlot.js
PERF/lib/src/lodash.min.js
PERF/lib/src/main_fasta.js
PERF/lib/src/main_fastq.js
PERF/lib/src/piePlot.js
PERF/lib/src/semantic.min.js
PERF/lib/src/slim-select.js
PERF/lib/src/tables_fasta.js
PERF/lib/src/tables_fastq.js
PERF/lib/styles/apexcharts.min.css
PERF/lib/styles/main.css
PERF/lib/styles/mini-default.min.css
PERF/lib/styles/multi-select.min.css
PERF/lib/styles/semantic.min.css
PERF/lib/styles/slim-select.css
perf_ssr-0.4.8.dist-info/LICENSE
perf_ssr-0.4.8.dist-info/METADATA
perf_ssr-0.4.8.dist-info/WHEEL
perf_ssr-0.4.8.dist-info/entry_points.txt
perf_ssr-0.4.8.dist-info/top_level.txt
perf_ssr-0.4.8.dist-info/RECORD
