Metadata-Version: 2.1
Name: perf-ssr
Version: 0.4.8
Summary: PERF is an exhaustive repeat finder
Home-page: https://github.com/rkmlab/perf
Author: Divya Tej Sowpati
Author-email: tej@ccmb.res.in
License: MIT
Keywords: ssr microsatellites
License-File: LICENSE
Requires-Dist: biopython (==1.69)
Requires-Dist: tqdm (>=4)
